jiemoutils
