Metadata-Version: 1.0
Name: jiemoutils
Version: 0.9
Summary: jiemo utils
Home-page: http://jiemo.co
Author: it_account@jiemodai.com
Author-email: it_account@jiemodai.com
License: UNKNOWN
Platform: UNKNOWN
